django_minirest-0.1.0.dist-info/DESCRIPTION.rst
django_minirest-0.1.0.dist-info/METADATA
django_minirest-0.1.0.dist-info/RECORD
django_minirest-0.1.0.dist-info/WHEEL
django_minirest-0.1.0.dist-info/metadata.json
django_minirest-0.1.0.dist-info/top_level.txt
minirest/__init__.py
minirest/conf.py
minirest/exceptions.py
minirest/loading.py
minirest/models.py
minirest/perms.py
minirest/urls.py
minirest/utils.py
minirest/views.py
