Metadata-Version: 2.0
Name: django-minirest
Version: 0.1.0
Summary: Micro rest framework
Home-page: https://github.com/vahaah/django-minirest
Author: Alex Vakhitov
Author-email: alex.vakhitov@gmail.com
License: BSD
Keywords: django-minirest
Platform: UNKNOWN
Classifier: Development Status :: 3 - Alpha
Classifier: Framework :: Django
Classifier: Framework :: Django :: 1.8
Classifier: Framework :: Django :: 1.9
Classifier: Intended Audience :: Developers
Classifier: License :: OSI Approved :: BSD License
Classifier: Natural Language :: English
Classifier: Programming Language :: Python :: 2
Classifier: Programming Language :: Python :: 2.7
Classifier: Programming Language :: Python :: 3
Classifier: Programming Language :: Python :: 3.3
Classifier: Programming Language :: Python :: 3.4
Classifier: Programming Language :: Python :: 3.5
Requires-Dist: djangorestframework (==3.3.2)
Requires-Dist: funcy (==1.7.1)
